pyinterpolate/__init__.py
pyinterpolate/core/__init__.py
pyinterpolate/core/data_models/__init__.py
pyinterpolate/core/data_models/blocks.py
pyinterpolate/core/data_models/centroid_poisson_kriging.py
pyinterpolate/core/data_models/experimental_variogram.py
pyinterpolate/core/data_models/point_support.py
pyinterpolate/core/data_models/point_support_distances.py
pyinterpolate/core/data_models/points.py
pyinterpolate/core/data_models/poisson_kriging.py
pyinterpolate/core/data_models/theoretical_variogram.py
pyinterpolate/core/pipelines/__init__.py
pyinterpolate/core/pipelines/block_filter.py
pyinterpolate/core/pipelines/interpolate.py
pyinterpolate/core/ptp_warnings/__init__.py
pyinterpolate/core/ptp_warnings/ptp_warnings.py
pyinterpolate/core/validators/__init__.py
pyinterpolate/core/validators/common.py
pyinterpolate/core/validators/custom_types.py
pyinterpolate/core/validators/experimental_semivariance.py
pyinterpolate/core/validators/experimental_semivariance_warnings.py
pyinterpolate/distance/__init__.py
pyinterpolate/distance/angular.py
pyinterpolate/distance/block.py
pyinterpolate/distance/gridding.py
pyinterpolate/distance/point.py
pyinterpolate/evaluate/__init__.py
pyinterpolate/evaluate/cross_validation.py
pyinterpolate/evaluate/metrics.py
pyinterpolate/idw/__init__.py
pyinterpolate/idw/idw.py
pyinterpolate/kriging/__init__.py
pyinterpolate/kriging/block/__init__.py
pyinterpolate/kriging/block/area_to_area_poisson_kriging.py
pyinterpolate/kriging/block/area_to_point_poisson_kriging.py
pyinterpolate/kriging/block/centroid_based_poisson_kriging.py
pyinterpolate/kriging/block/weights.py
pyinterpolate/kriging/point/__init__.py
pyinterpolate/kriging/point/indicator.py
pyinterpolate/kriging/point/ordinary.py
pyinterpolate/kriging/point/simple.py
pyinterpolate/kriging/point/universal.py
pyinterpolate/kriging/utils/__init__.py
pyinterpolate/kriging/utils/errors.py
pyinterpolate/kriging/utils/point_kriging_solve.py
pyinterpolate/semivariogram/__init__.py
pyinterpolate-1.2.1.dist-info/licenses/LICENSE.md
pyinterpolate-1.2.1.dist-info/METADATA
pyinterpolate-1.2.1.dist-info/WHEEL
pyinterpolate-1.2.1.dist-info/top_level.txt
pyinterpolate-1.2.1.dist-info/RECORD
