Metadata-Version: 2.4
Name: pyinterpolate
Version: 1.2.1
Author-email: Szymon Moliński <simon@dataverselabs.com>
Maintainer: Szymon Moliński
Project-URL: Documentation, https://pyinterpolate.readthedocs.io/en/latest/index.html
Project-URL: Repository, https://github.com/DataverseLabs/pyinterpolate
Project-URL: Changelog, https://github.com/DataverseLabs/pyinterpolate/blob/main/CHANGELOG.rst
Classifier: Development Status :: 5 - Production/Stable
Classifier: Programming Language :: Python :: 3.10
Classifier: Programming Language :: Python :: 3.11
Classifier: Programming Language :: Python :: 3.12
Classifier: Programming Language :: Python :: 3.13
Classifier: License :: OSI Approved :: MIT License
Classifier: Operating System :: OS Independent
License-File: LICENSE.md
Requires-Dist: pydantic
Requires-Dist: tqdm
Requires-Dist: geopandas
Requires-Dist: scipy
Requires-Dist: prettytable
Requires-Dist: numpy
Requires-Dist: matplotlib
Requires-Dist: dask
Dynamic: license-file
